Workbook

Sheet Inputs_Assumptions
A1: Marketing Campaign A/B Test: Commercial Impact Model
A2: [HYPOTHETICAL ASSUMPTIONS - FOR PLANNING & SCENARIO EVALUATION ONLY]
A4: 1. Financial & Unit Economics Assumptions (User Inputs)
A5: Parameter | B5: Base Case | C5: Unit | D5: Sensitivity Range / Notes
A6: Gross Margin per Conversion | B6: 40 | C6: $ / order | D6: Sensitivity tested from $5 to $100
A7: Cost per Thousand Impressions (CPM) | B7: 2 | C7: $ / 1k impressions | D7: Sensitivity tested from $1 to $10
A8: Cost per Single Ad Impression | B8: =Inputs_Assumptions!B7/1000 -> 0.002 | C8: $ / impression | D8: Derived formula (= CPM / 1,000)
A10: 2. Empirical Experiment Metrics (from Executed A/B Test Data)
A11: Experiment Metric | B11: Observed Value | C11: Unit | D11: Source / Derivation
A12: Treatment Population (Ad Cohort) | B12: 564577 | C12: users | D12: Executed SQL / SQLite database
A13: Control Population (PSA Cohort) | B13: 23524 | C13: users | D13: Executed SQL / SQLite database
A14: Treatment Total Ad Impressions Served | B14: 14014692 | C14: impressions | D14: Sum of total_ads in Treatment cohort
A15: Control Baseline Conversion Rate | B15: 0.017854 | C15: rate | D15: 420 conversions / 23,524 users (1.7854%)
A16: Treatment Observed Conversion Rate | B16: 0.025547 | C16: rate | D16: 14,423 conversions / 564,577 users (2.5547%)
A17: Expected Baseline Conversions (Without Campaign) | B17: =ROUND(B12*B15, 0) -> 10080 | C17: conversions | D17: Formula: Treatment Users * Control CR
A18: Treatment Total Observed Conversions | B18: 14423 | C18: conversions | D18: Observed buyers in Treatment cohort
A19: Incremental Conversions (Point Estimate - Base Case) | B19: =B18-B17 -> 4343 | C19: conversions | D19: Observed Treatment - Expected Baseline
A20: Incremental Conversions (Low - 95% CI Lower Bound) | B20: 3360 | C20: conversions | D20: 564,577 users * 0.5951% pts lift (conservative bound)
A21: Incremental Conversions (High - 95% CI Upper Bound) | B21: 5326 | C21: conversions | D21: 564,577 users * 0.9434% pts lift (optimistic bound)
A24: 3. Frequency Capping Parameters (Cap at 100 Impressions)
A25: Users Exposed to > 100 Ads | B25: 22054 | C25: users | D25: Treatment users seeing > 100 ads
A26: Uncapped Impressions in 100+ Tier | B26: 4058074 | C26: impressions | D26: Current impressions served to 100+ tier
A27: Capped Impressions in 100+ Tier (Cap @ 100) | B27: =B25*100 -> 2205400 | C27: impressions | D27: Formula: 22,054 users * 100 ads max
A28: Impressions Saved via 100-Ad Cap | B28: =B26-B27 -> 1852674 | C28: impressions | D28: Reduction in impressions beyond the 100th ad
A29: Total Campaign Impressions with 100-Ad Cap | B29: =B14-B28 -> 12162018 | C29: impressions | D29: 14,014,692 uncapped - 1,852,674 saved beyond 100th ad
A30: Incremental Conversions Generated in 100+ Tier | B30: 1159 | C30: conversions | D30: Current causal lift in 100+ tier (44.2% rel lift)

Sheet Executive_Summary
A1: Executive Campaign Performance & Break-Even Analysis
A2: [DYNAMIC FORMULAS DRIVEN BY INPUTS SHEET - HYPOTHETICAL ASSUMPTIONS]
A4: 1. Financial Performance Across Statistical Confidence Bounds
A5: Financial Metric | B5: Conservative (95% CI Low) | C5: Base Case (Point Estimate) | D5: Optimistic (95% CI High) | E5: Formula Derivation
A6: Incremental Conversions | B6: =Inputs_Assumptions!B20 -> 3360 | C6: =Inputs_Assumptions!B19 -> 4343 | D6: =Inputs_Assumptions!B21 -> 5326 | E6: From statistical test (CI lower / point / CI upper)
A7: Gross Margin per Conversion | B7: =Inputs_Assumptions!B6 -> 40 | C7: =Inputs_Assumptions!B6 -> 40 | D7: =Inputs_Assumptions!B6 -> 40 | E7: Hypothetical user input ($40 base margin)
A8: Incremental Gross Profit | B8: =B6*B7 -> 134400 | C8: =C6*C7 -> 173720 | D8: =D6*D7 -> 213040 | E8: Incremental Conversions * Gross Margin per Conversion
A9: Total Ad Impressions Served | B9: =Inputs_Assumptions!B14 -> 14014692 | C9: =Inputs_Assumptions!B14 -> 14014692 | D9: =Inputs_Assumptions!B14 -> 14014692 | E9: 14,014,692 impressions (empirical)
A10: Cost per 1,000 Impressions (CPM) | B10: =Inputs_Assumptions!B7 -> 2 | C10: =Inputs_Assumptions!B7 -> 2 | D10: =Inputs_Assumptions!B7 -> 2 | E10: Hypothetical user input ($2.00 base)
A11: Total Campaign Media Spend | B11: =(B9/1000)*B10 -> 28029.384 | C11: =(C9/1000)*C10 -> 28029.384 | D11: =(D9/1000)*D10 -> 28029.384 | E11: (Total Impressions / 1,000) * CPM
A12: Net Incremental Profit | B12: =B8-B11 -> 106370.62 | C12: =C8-C11 -> 145690.62 | D12: =D8-D11 -> 185010.62 | E12: Incremental Gross Profit - Total Media Spend
A13: Margin-based Return on Ad Spend (ROAS) | B13: =B8/B11 -> 4.794968 | C13: =C8/C11 -> 6.1977816 | D13: =D8/D11 -> 7.6005951 | E13: Incremental Gross Profit / Total Media Spend
A14: Cost per Incremental Conversion (CAC) | B14: =B11/B6 -> 8.3420786 | C14: =C11/C6 -> 6.4539222 | D14: =D11/D6 -> 5.2627458 | E14: Total Media Spend / Incremental Conversions
A17: 2. Explicit Break-Even Analysis
A18: Break-Even Metric | B18: Conservative (95% CI Low) | C18: Base Case | D18: Optimistic (95% CI High) | E18: Business Interpretation
A19: Break-Even CPM (Maximum viable CPM at $40 margin) | B19: =(B6*Inputs_Assumptions!B6)/(Inputs_Assumptions!B14/1000) -> 9.589936 | C19: =(C6*Inputs_Assumptions!B6)/(Inputs_Assumptions!B14/1000) -> 12.395563 | D19: =(D6*Inputs_Assumptions!B6)/(Inputs_Assumptions!B14/1000) -> 15.20119 | E19: If actual CPM exceeds this threshold, campaign is net-negative
A20: Break-Even Margin (Minimum required margin at $2.00 CPM) | B20: =B11/B6 -> 8.3420786 | C20: =C11/C6 -> 6.4539222 | D20: =D11/D6 -> 5.2627458 | E20: If gross margin per order falls below this value, campaign loses money

Sheet Sensitivity_Matrix
A1: 2D Sensitivity Matrix: Net Incremental Profit ($)
A2: [BASE CASE: 4,343 INCREMENTAL CONVERSIONS | 14,014,692 IMPRESSIONS - ALL FORMULAS LIVE]
A4: CPM \ Margin | B4: 5 | C4: 10 | D4: 15 | E4: 20 | F4: 25 | G4: 30 | H4: 40 | I4: 50 | J4: 60 | K4: 75 | L4: 100
A5: 1 | B5: =(Inputs_Assumptions!$B$19*B$4)-((Inputs_Assumptions!$B$14/1000)*$A5) -> 7700.308 | C5: =(Inputs_Assumptions!$B$19*C$4)-((Inputs_Assumptions!$B$14/1000)*$A5) -> 29415.308 | D5: =(Inputs_Assumptions!$B$19*D$4)-((Inputs_Assumptions!$B$14/1000)*$A5) -> 51130.308 | E5: =(Inputs_Assumptions!$B$19*E$4)-((Inputs_Assumptions!$B$14/1000)*$A5) -> 72845.308 | F5: =(Inputs_Assumptions!$B$19*F$4)-((Inputs_Assumptions!$B$14/1000)*$A5) -> 94560.308 | G5: =(Inputs_Assumptions!$B$19*G$4)-((Inputs_Assumptions!$B$14/1000)*$A5) -> 116275.31 | H5: =(Inputs_Assumptions!$B$19*H$4)-((Inputs_Assumptions!$B$14/1000)*$A5) -> 159705.31 | I5: =(Inputs_Assumptions!$B$19*I$4)-((Inputs_Assumptions!$B$14/1000)*$A5) -> 203135.31 | ... L5: =(Inputs_Assumptions!$B$19*L$4)-((Inputs_Assumptions!$B$14/1000)*$A5) -> 420285.31
A6: 1.5 | B6: =(Inputs_Assumptions!$B$19*B$4)-((Inputs_Assumptions!$B$14/1000)*$A6) -> 692.962 | C6: =(Inputs_Assumptions!$B$19*C$4)-((Inputs_Assumptions!$B$14/1000)*$A6) -> 22407.962 | D6: =(Inputs_Assumptions!$B$19*D$4)-((Inputs_Assumptions!$B$14/1000)*$A6) -> 44122.962 | E6: =(Inputs_Assumptions!$B$19*E$4)-((Inputs_Assumptions!$B$14/1000)*$A6) -> 65837.962 | F6: =(Inputs_Assumptions!$B$19*F$4)-((Inputs_Assumptions!$B$14/1000)*$A6) -> 87552.962 | G6: =(Inputs_Assumptions!$B$19*G$4)-((Inputs_Assumptions!$B$14/1000)*$A6) -> 109267.96 | H6: =(Inputs_Assumptions!$B$19*H$4)-((Inputs_Assumptions!$B$14/1000)*$A6) -> 152697.96 | I6: =(Inputs_Assumptions!$B$19*I$4)-((Inputs_Assumptions!$B$14/1000)*$A6) -> 196127.96 | ... L6: =(Inputs_Assumptions!$B$19*L$4)-((Inputs_Assumptions!$B$14/1000)*$A6) -> 413277.96
A7: 2 | B7: =(Inputs_Assumptions!$B$19*B$4)-((Inputs_Assumptions!$B$14/1000)*$A7) -> -6314.384 | C7: =(Inputs_Assumptions!$B$19*C$4)-((Inputs_Assumptions!$B$14/1000)*$A7) -> 15400.616 | D7: =(Inputs_Assumptions!$B$19*D$4)-((Inputs_Assumptions!$B$14/1000)*$A7) -> 37115.616 | E7: =(Inputs_Assumptions!$B$19*E$4)-((Inputs_Assumptions!$B$14/1000)*$A7) -> 58830.616 | F7: =(Inputs_Assumptions!$B$19*F$4)-((Inputs_Assumptions!$B$14/1000)*$A7) -> 80545.616 | G7: =(Inputs_Assumptions!$B$19*G$4)-((Inputs_Assumptions!$B$14/1000)*$A7) -> 102260.62 | H7: =(Inputs_Assumptions!$B$19*H$4)-((Inputs_Assumptions!$B$14/1000)*$A7) -> 145690.62 | I7: =(Inputs_Assumptions!$B$19*I$4)-((Inputs_Assumptions!$B$14/1000)*$A7) -> 189120.62 | ... L7: =(Inputs_Assumptions!$B$19*L$4)-((Inputs_Assumptions!$B$14/1000)*$A7) -> 406270.62
A8: 2.5 | B8: =(Inputs_Assumptions!$B$19*B$4)-((Inputs_Assumptions!$B$14/1000)*$A8) -> -13321.73 | C8: =(Inputs_Assumptions!$B$19*C$4)-((Inputs_Assumptions!$B$14/1000)*$A8) -> 8393.27 | D8: =(Inputs_Assumptions!$B$19*D$4)-((Inputs_Assumptions!$B$14/1000)*$A8) -> 30108.27 | E8: =(Inputs_Assumptions!$B$19*E$4)-((Inputs_Assumptions!$B$14/1000)*$A8) -> 51823.27 | F8: =(Inputs_Assumptions!$B$19*F$4)-((Inputs_Assumptions!$B$14/1000)*$A8) -> 73538.27 | G8: =(Inputs_Assumptions!$B$19*G$4)-((Inputs_Assumptions!$B$14/1000)*$A8) -> 95253.27 | H8: =(Inputs_Assumptions!$B$19*H$4)-((Inputs_Assumptions!$B$14/1000)*$A8) -> 138683.27 | I8: =(Inputs_Assumptions!$B$19*I$4)-((Inputs_Assumptions!$B$14/1000)*$A8) -> 182113.27 | ... L8: =(Inputs_Assumptions!$B$19*L$4)-((Inputs_Assumptions!$B$14/1000)*$A8) -> 399263.27
A9: 3 | B9: =(Inputs_Assumptions!$B$19*B$4)-((Inputs_Assumptions!$B$14/1000)*$A9) -> -20329.076 | C9: =(Inputs_Assumptions!$B$19*C$4)-((Inputs_Assumptions!$B$14/1000)*$A9) -> 1385.924 | D9: =(Inputs_Assumptions!$B$19*D$4)-((Inputs_Assumptions!$B$14/1000)*$A9) -> 23100.924 | E9: =(Inputs_Assumptions!$B$19*E$4)-((Inputs_Assumptions!$B$14/1000)*$A9) -> 44815.924 | F9: =(Inputs_Assumptions!$B$19*F$4)-((Inputs_Assumptions!$B$14/1000)*$A9) -> 66530.924 | G9: =(Inputs_Assumptions!$B$19*G$4)-((Inputs_Assumptions!$B$14/1000)*$A9) -> 88245.924 | H9: =(Inputs_Assumptions!$B$19*H$4)-((Inputs_Assumptions!$B$14/1000)*$A9) -> 131675.92 | I9: =(Inputs_Assumptions!$B$19*I$4)-((Inputs_Assumptions!$B$14/1000)*$A9) -> 175105.92 | ... L9: =(Inputs_Assumptions!$B$19*L$4)-((Inputs_Assumptions!$B$14/1000)*$A9) -> 392255.92
A10: 4 | B10: =(Inputs_Assumptions!$B$19*B$4)-((Inputs_Assumptions!$B$14/1000)*$A10) -> -34343.768 | C10: =(Inputs_Assumptions!$B$19*C$4)-((Inputs_Assumptions!$B$14/1000)*$A10) -> -12628.768 | D10: =(Inputs_Assumptions!$B$19*D$4)-((Inputs_Assumptions!$B$14/1000)*$A10) -> 9086.232 | E10: =(Inputs_Assumptions!$B$19*E$4)-((Inputs_Assumptions!$B$14/1000)*$A10) -> 30801.232 | F10: =(Inputs_Assumptions!$B$19*F$4)-((Inputs_Assumptions!$B$14/1000)*$A10) -> 52516.232 | G10: =(Inputs_Assumptions!$B$19*G$4)-((Inputs_Assumptions!$B$14/1000)*$A10) -> 74231.232 | H10: =(Inputs_Assumptions!$B$19*H$4)-((Inputs_Assumptions!$B$14/1000)*$A10) -> 117661.23 | I10: =(Inputs_Assumptions!$B$19*I$4)-((Inputs_Assumptions!$B$14/1000)*$A10) -> 161091.23 | ... L10: =(Inputs_Assumptions!$B$19*L$4)-((Inputs_Assumptions!$B$14/1000)*$A10) -> 378241.23
A11: 5 | B11: =(Inputs_Assumptions!$B$19*B$4)-((Inputs_Assumptions!$B$14/1000)*$A11) -> -48358.46 | C11: =(Inputs_Assumptions!$B$19*C$4)-((Inputs_Assumptions!$B$14/1000)*$A11) -> -26643.46 | D11: =(Inputs_Assumptions!$B$19*D$4)-((Inputs_Assumptions!$B$14/1000)*$A11) -> -4928.46 | E11: =(Inputs_Assumptions!$B$19*E$4)-((Inputs_Assumptions!$B$14/1000)*$A11) -> 16786.54 | F11: =(Inputs_Assumptions!$B$19*F$4)-((Inputs_Assumptions!$B$14/1000)*$A11) -> 38501.54 | G11: =(Inputs_Assumptions!$B$19*G$4)-((Inputs_Assumptions!$B$14/1000)*$A11) -> 60216.54 | H11: =(Inputs_Assumptions!$B$19*H$4)-((Inputs_Assumptions!$B$14/1000)*$A11) -> 103646.54 | I11: =(Inputs_Assumptions!$B$19*I$4)-((Inputs_Assumptions!$B$14/1000)*$A11) -> 147076.54 | ... L11: =(Inputs_Assumptions!$B$19*L$4)-((Inputs_Assumptions!$B$14/1000)*$A11) -> 364226.54
A12: 6 | B12: =(Inputs_Assumptions!$B$19*B$4)-((Inputs_Assumptions!$B$14/1000)*$A12) -> -62373.152 | C12: =(Inputs_Assumptions!$B$19*C$4)-((Inputs_Assumptions!$B$14/1000)*$A12) -> -40658.152 | D12: =(Inputs_Assumptions!$B$19*D$4)-((Inputs_Assumptions!$B$14/1000)*$A12) -> -18943.152 | E12: =(Inputs_Assumptions!$B$19*E$4)-((Inputs_Assumptions!$B$14/1000)*$A12) -> 2771.848 | F12: =(Inputs_Assumptions!$B$19*F$4)-((Inputs_Assumptions!$B$14/1000)*$A12) -> 24486.848 | G12: =(Inputs_Assumptions!$B$19*G$4)-((Inputs_Assumptions!$B$14/1000)*$A12) -> 46201.848 | H12: =(Inputs_Assumptions!$B$19*H$4)-((Inputs_Assumptions!$B$14/1000)*$A12) -> 89631.848 | I12: =(Inputs_Assumptions!$B$19*I$4)-((Inputs_Assumptions!$B$14/1000)*$A12) -> 133061.85 | ... L12: =(Inputs_Assumptions!$B$19*L$4)-((Inputs_Assumptions!$B$14/1000)*$A12) -> 350211.85
A13: 8 | B13: =(Inputs_Assumptions!$B$19*B$4)-((Inputs_Assumptions!$B$14/1000)*$A13) -> -90402.536 | C13: =(Inputs_Assumptions!$B$19*C$4)-((Inputs_Assumptions!$B$14/1000)*$A13) -> -68687.536 | D13: =(Inputs_Assumptions!$B$19*D$4)-((Inputs_Assumptions!$B$14/1000)*$A13) -> -46972.536 | E13: =(Inputs_Assumptions!$B$19*E$4)-((Inputs_Assumptions!$B$14/1000)*$A13) -> -25257.536 | F13: =(Inputs_Assumptions!$B$19*F$4)-((Inputs_Assumptions!$B$14/1000)*$A13) -> -3542.536 | G13: =(Inputs_Assumptions!$B$19*G$4)-((Inputs_Assumptions!$B$14/1000)*$A13) -> 18172.464 | H13: =(Inputs_Assumptions!$B$19*H$4)-((Inputs_Assumptions!$B$14/1000)*$A13) -> 61602.464 | I13: =(Inputs_Assumptions!$B$19*I$4)-((Inputs_Assumptions!$B$14/1000)*$A13) -> 105032.46 | ... L13: =(Inputs_Assumptions!$B$19*L$4)-((Inputs_Assumptions!$B$14/1000)*$A13) -> 322182.46
A14: 10 | B14: =(Inputs_Assumptions!$B$19*B$4)-((Inputs_Assumptions!$B$14/1000)*$A14) -> -118431.92 | C14: =(Inputs_Assumptions!$B$19*C$4)-((Inputs_Assumptions!$B$14/1000)*$A14) -> -96716.92 | D14: =(Inputs_Assumptions!$B$19*D$4)-((Inputs_Assumptions!$B$14/1000)*$A14) -> -75001.92 | E14: =(Inputs_Assumptions!$B$19*E$4)-((Inputs_Assumptions!$B$14/1000)*$A14) -> -53286.92 | F14: =(Inputs_Assumptions!$B$19*F$4)-((Inputs_Assumptions!$B$14/1000)*$A14) -> -31571.92 | G14: =(Inputs_Assumptions!$B$19*G$4)-((Inputs_Assumptions!$B$14/1000)*$A14) -> -9856.92 | H14: =(Inputs_Assumptions!$B$19*H$4)-((Inputs_Assumptions!$B$14/1000)*$A14) -> 33573.08 | I14: =(Inputs_Assumptions!$B$19*I$4)-((Inputs_Assumptions!$B$14/1000)*$A14) -> 77003.08 | ... L14: =(Inputs_Assumptions!$B$19*L$4)-((Inputs_Assumptions!$B$14/1000)*$A14) -> 294153.08
A15: 12 | B15: =(Inputs_Assumptions!$B$19*B$4)-((Inputs_Assumptions!$B$14/1000)*$A15) -> -146461.3 | C15: =(Inputs_Assumptions!$B$19*C$4)-((Inputs_Assumptions!$B$14/1000)*$A15) -> -124746.3 | D15: =(Inputs_Assumptions!$B$19*D$4)-((Inputs_Assumptions!$B$14/1000)*$A15) -> -103031.3 | E15: =(Inputs_Assumptions!$B$19*E$4)-((Inputs_Assumptions!$B$14/1000)*$A15) -> -81316.304 | F15: =(Inputs_Assumptions!$B$19*F$4)-((Inputs_Assumptions!$B$14/1000)*$A15) -> -59601.304 | G15: =(Inputs_Assumptions!$B$19*G$4)-((Inputs_Assumptions!$B$14/1000)*$A15) -> -37886.304 | H15: =(Inputs_Assumptions!$B$19*H$4)-((Inputs_Assumptions!$B$14/1000)*$A15) -> 5543.696 | I15: =(Inputs_Assumptions!$B$19*I$4)-((Inputs_Assumptions!$B$14/1000)*$A15) -> 48973.696 | ... L15: =(Inputs_Assumptions!$B$19*L$4)-((Inputs_Assumptions!$B$14/1000)*$A15) -> 266123.7

Sheet Scenario_Comparison
A1: Strategic Scenario Analysis: Uncapped vs. Frequency-Capped Rollout
A2: [CAP EVALUATED AT 100 IMPRESSIONS ACROSS 100%, 75%, AND 50% RETENTION ASSUMPTIONS]
A5: Scenario Strategy | B5: Total Impressions | C5: Media Spend (@ $2 CPM) | D5: Incremental Conversions | E5: Incremental Gross Profit (@ $40 Margin) | F5: Net Incremental Profit | G5: Margin-based ROAS | H5: Spend Savings vs Uncapped | I5: Strategic Assessment
A6: Scenario A: Full Uncapped Rollout | B6: =Inputs_Assumptions!B14 -> 14014692 | C6: =(B6/1000)*Inputs_Assumptions!B7 -> 28029.384 | D6: =Inputs_Assumptions!B19 -> 4343 | E6: =D6*Inputs_Assumptions!B6 -> 173720 | F6: =E6-C6 -> 145690.62 | G6: =E6/C6 -> 6.1977816 | H6: 0 | I6: Standard baseline; captures full +$145.7k net profit without conversion risk
A7: Scenario B1: 100-Ad Cap (100% Conversions Retained) | B7: =Inputs_Assumptions!B29 -> 12162018 | C7: =(B7/1000)*Inputs_Assumptions!B7 -> 24324.036 | D7: =Inputs_Assumptions!B19 -> 4343 | E7: =D7*Inputs_Assumptions!B6 -> 173720 | F7: =E7-C7 -> 149395.96 | G7: =E7/C7 -> 7.1419069 | H7: =C6-C7 -> 3705.348 | I7: Optimistic cap scenario; saves $3,705 spend with zero conversion loss
A8: Scenario B2: 100-Ad Cap (75% Conversions Retained) | B8: =Inputs_Assumptions!B29 -> 12162018 | C8: =(B8/1000)*Inputs_Assumptions!B7 -> 24324.036 | D8: =Inputs_Assumptions!B19-(Inputs_Assumptions!B30*0.25) -> 4053.25 | E8: =D8*Inputs_Assumptions!B6 -> 162130 | F8: =E8-C8 -> 137805.96 | G8: =E8/C8 -> 6.6654235 | H8: =C6-C8 -> 3705.348 | I8: Conservative cap scenario; loses 290 orders ($11.6k) vs $3.7k saved
A9: Scenario B3: 100-Ad Cap (50% Conversions Retained) | B9: =Inputs_Assumptions!B29 -> 12162018 | C9: =(B9/1000)*Inputs_Assumptions!B7 -> 24324.036 | D9: =Inputs_Assumptions!B19-(Inputs_Assumptions!B30*0.5) -> 3763.5 | E9: =D9*Inputs_Assumptions!B6 -> 150540 | F9: =E9-C9 -> 126215.96 | G9: =E9/C9 -> 6.18894 | H9: =C6-C9 -> 3705.348 | I9: Pessimistic cap scenario; severe conversion leakage leads to lower profit

Sheet Timing_Hypothesis
A1: Scenario C: Day-of-Week Budget Shift (Exploratory Operational Hypothesis)
A2: [CAVEAT: THURSDAY AND SUNDAY WERE NOT STATISTICALLY SIGNIFICANT AFTER BONFERRONI. THIS IS A HYPOTHESIS TO TEST VIA RANDOMIZED HOLDOUT, NOT AN OPERATIONAL ROLLOUT RULE.]
A5: Day of Week | B5: Treatment Users | C5: Observed Treatment CR | D5: Control CR | E5: Observed Lift (% pts) | F5: Bonferroni Verdict | G5: Current Media Spend (@ $2 CPM) | H5: Operational Holdout Test Plan
A6: Monday | B6: 83571 | C6: 0.033241 | D6: 0.022559 | E6: 0.010682 | F6: Significant (p=0.0005) | G6: =(B6*24.8/1000)*Inputs_Assumptions!$B$7 -> 4145.1216 | H6: Maintain high bid priority; high-volume driver
A7: Tuesday | B7: 74572 | C7: 0.03044 | D7: 0.014448 | E7: 0.015992 | F7: Significant (p<0.0001) | G7: =(B7*24.8/1000)*Inputs_Assumptions!$B$7 -> 3698.7712 | H7: Primary candidate for budget expansion (+111% lift)
A8: Wednesday | B8: 77418 | C8: 0.025356 | D8: 0.015759 | E8: 0.009597 | F8: Significant (p=0.0004) | G8: =(B8*24.8/1000)*Inputs_Assumptions!$B$7 -> 3839.9328 | H8: Maintain steady allocation
A9: Thursday | B9: 79077 | C9: 0.021637 | D9: 0.02023 | E9: 0.001407 | F9: NOT Significant (p=0.555) | G9: =(B9*24.8/1000)*Inputs_Assumptions!$B$7 -> 3922.2192 | H9: Run randomized holdout: reduce bids 25% for 50% users
A10: Friday | B10: 88805 | C10: 0.022465 | D10: 0.016303 | E10: 0.006162 | F10: Borderline (p=0.012) | G10: =(B10*24.8/1000)*Inputs_Assumptions!$B$7 -> 4404.728 | H10: High volume, lower lift; monitor efficiency
A11: Saturday | B11: 78802 | C11: 0.021307 | D11: 0.013996 | E11: 0.007311 | F11: Borderline (p=0.0075) | G11: =(B11*24.8/1000)*Inputs_Assumptions!$B$7 -> 3908.5792 | H11: Weekend baseline
A12: Sunday | B12: 82332 | C12: 0.02462 | D12: 0.020595 | E12: 0.004025 | F12: NOT Significant (p=0.157) | G12: =(B12*24.8/1000)*Inputs_Assumptions!$B$7 -> 4083.6672 | H12: Run randomized holdout: reduce bids 25% for 50% users
